goopywoopy/__init__.py
goopywoopy/abc/__init__.py
goopywoopy/abc/__init__.pyi
goopywoopy/abc/feature.py
goopywoopy/abc/feature.pyi
goopywoopy/classtools/__init__.py
goopywoopy/classtools/_possibility.py
goopywoopy/classtools/_possibility.pyi
goopywoopy/classtools/_property.py
goopywoopy/classtools/_property.pyi
goopywoopy/classtools/exceptions.py
goopywoopy/progress/__init__.py
goopywoopy/progress/bar/__init__.py
goopywoopy/progress/bar/__init__.pyi
goopywoopy/progress/bar/core.py
goopywoopy/progress/bar/core.pyi
goopywoopy/progress/bar/types.py
goopywoopy/progress/bar/types.pyi
goopywoopy/progress/bar/_features/__init__.py
goopywoopy/progress/bar/_features/__init__.pyi
goopywoopy/progress/bar/_features/decoy.py
goopywoopy/progress/bar/_features/decoy.pyi
goopywoopy/progress/bar/_features/logging.py
goopywoopy/progress/bar/_features/logging.pyi
goopywoopy/progress/bar/_features/precursor.py
goopywoopy/progress/bar/_features/precursor.pyi
goopywoopy/progress/bar/_features/shellexec.py
goopywoopy/progress/bar/_features/shellexec.pyi
goopywoopy/progress/bar/_features/threads.py
goopywoopy/progress/bar/_precursor/__init__.py
goopywoopy/progress/bar/_precursor/__init__.pyi
goopywoopy/progress/bar/_precursor/core.py
goopywoopy/progress/bar/_precursor/core.pyi
goopywoopy/progress/bar/utils/__init__.py
goopywoopy/progress/bar/utils/__init__.pyi
goopywoopy/progress/bar/utils/splitter.py
goopywoopy/progress/bar/utils/splitter.pyi
goopywoopy/progress/bar/widgets/__init__.py
goopywoopy/progress/bar/widgets/__init__.pyi
goopywoopy/progress/bar/widgets/abc.py
goopywoopy/progress/bar/widgets/abc.pyi
goopywoopy/progress/bar/widgets/core.py
goopywoopy/progress/bar/widgets/core.pyi
goopywoopy/tools/__init__.py
goopywoopy/tools/terminal/__init__.py
goopywoopy/tools/terminal/_colorize.py
goopywoopy/tools/terminal/_colorize.pyi
goopywoopy/tools/terminal/_size.py
goopywoopy/tools/terminal/_size.pyi
goopywoopy/tools/utilities/__init__.py
goopywoopy/tools/utilities/_random.py
goopywoopy-0.1.0.dist-info/LICENSE
goopywoopy-0.1.0.dist-info/METADATA
goopywoopy-0.1.0.dist-info/WHEEL
goopywoopy-0.1.0.dist-info/top_level.txt
goopywoopy-0.1.0.dist-info/RECORD
