Metadata-Version: 2.2
Name: goopywoopy
Version: 0.1.0
Summary: A kit containing tools for better programming.
Author-email: Soumyo Deep Gupta <deep.main.ac@gmail.com>
Maintainer-email: Soumyo Deep Gupta <deep.main.ac@gmail.com>
License: MIT License
Project-URL: GitHub, https://github.com/d33p0st/goopywoopy
Project-URL: Issues, https://github.com/d33p0st/goopywoopy/issues
Project-URL: Pull-Request, https://github.com/d33p0st/goopywoopy/pulls
Keywords: d33p0st,goopywoopy,modstore,module,kit,OOP,object,ABC
Requires-Python: >=3.8
License-File: LICENSE
Requires-Dist: colorama
